{
    "key": "sidebar_items",
    "title": "Sidebar",
    "fields": [
        {
            "key": "sidebar_item",
            "label": "Sidebar Item",
            "name": "sidebar_item",
            "type": "repeater",
            "instructions": "",
            "required": 0,
            "conditional_logic": 0,
            "wrapper": {
                "width": "",
                "class": "",
                "id": ""
            },
            "collapsed": "",
            "min": 0,
            "max": 0,
            "layout": "block",
            "button_label": "Add Item",
            "sub_fields": [
                {
                    "key": "sidebar_item_type",
                    "label": "Item Type",
                    "name": "sidebar_item_type",
                    "type": "select",
                    "instructions": "",
                    "required": 1,
                    "conditional_logic": 0,
                    "wrapper": {
                        "width": "",
                        "class": "",
                        "id": ""
                    },
                    "choices": {
                        "button_in": "Button (Internal)",
                        "button_ex": "Button (External)",
                        "content": "Content",
                        "student": "Student Stories"
                    },
                    "default_value": [],
                    "allow_null": 0,
                    "multiple": 0,
                    "ui": 0,
                    "ajax": 0,
                    "return_format": "value",
                    "placeholder": ""
                },
                {
                    "key": "button_text",
                    "label": "Button Text",
                    "name": "button_text",
                    "type": "text",
                    "instructions": "",
                    "required": 1,
                    "conditional_logic": [
                        [
                            {
                                "field": "sidebar_item_type",
                                "operator": "==",
                                "value": "button_in"
                            }
                        ],
                        [
                            {
                                "field": "sidebar_item_type",
                                "operator": "==",
                                "value": "button_ex"
                            }
                        ]
                    ],
                    "wrapper": {
                        "width": "",
                        "class": "",
                        "id": ""
                    },
                    "default_value": "",
                    "placeholder": "",
                    "prepend": "",
                    "append": "",
                    "maxlength": ""
                },
                {
                    "key": "sidebar_button_ex",
                    "label": "URL",
                    "name": "sidebar_button_ex",
                    "type": "url",
                    "instructions": "",
                    "required": 1,
                    "conditional_logic": [
                        [
                            {
                                "field": "sidebar_item_type",
                                "operator": "==",
                                "value": "button_ex"
                            }
                        ]
                    ],
                    "wrapper": {
                        "width": "",
                        "class": "",
                        "id": ""
                    },
                    "default_value": "",
                    "placeholder": ""
                },
                {
                    "key": "sidebar_button_in",
                    "label": "Page Reference",
                    "name": "sidebar_button_in",
                    "type": "page_link",
                    "instructions": "",
                    "required": 0,
                    "conditional_logic": [
                        [
                            {
                                "field": "sidebar_item_type",
                                "operator": "==",
                                "value": "button_in"
                            }
                        ]
                    ],
                    "wrapper": {
                        "width": "",
                        "class": "",
                        "id": ""
                    },
                    "post_type": [],
                    "taxonomy": [],
                    "allow_null": 0,
                    "allow_archives": 1,
                    "multiple": 0
                },
                {
                    "key": "sidebar_content",
                    "label": "Content",
                    "name": "sidebar_content",
                    "type": "wysiwyg",
                    "instructions": "",
                    "required": 0,
                    "conditional_logic": [
                        [
                            {
                                "field": "sidebar_item_type",
                                "operator": "==",
                                "value": "content"
                            }
                        ]
                    ],
                    "wrapper": {
                        "width": "",
                        "class": "",
                        "id": ""
                    },
                    "default_value": "",
                    "tabs": "all",
                    "toolbar": "full",
                    "media_upload": 1,
                    "delay": 0
                },
                {
                    "key": "sidebar_item_student",
                    "label": "Student Stories",
                    "name": "",
                    "type": "message",
                    "instructions": "",
                    "required": 0,
                    "conditional_logic": [
                        [
                            {
                                "field": "sidebar_item_type",
                                "operator": "==",
                                "value": "student"
                            }
                        ]
                    ],
                    "wrapper": {
                        "width": "",
                        "class": "",
                        "id": ""
                    },
                    "message": "Student Stories will automatically render here. This should only be inserted once in the sidebar.",
                    "new_lines": "",
                    "esc_html": 0
                }
            ]
        }
    ],
    "location": [
        [
            {
                "param": "options_page",
                "operator": "==",
                "value": "ualbany"
            }
        ]
    ],
    "menu_order": 0,
    "position": "normal",
    "style": "default",
    "label_placement": "top",
    "instruction_placement": "label",
    "hide_on_screen": "",
    "active": 1,
    "description": "",
    "modified": 1528140867
}